simple_library/__init__.py
simple_library/module.py
simple_library-0.1.2.dist-info/METADATA
simple_library-0.1.2.dist-info/WHEEL
simple_library-0.1.2.dist-info/RECORD
