Metadata-Version: 2.1
Name: simple-library
Version: 0.1.2
Summary: simple library to test eBPF sandboxing
Author: MOUAD KONDAH
Author-email: kondah.mouad@gmail.com
Requires-Python: >=3.8,<4.0
Classifier: Programming Language :: Python :: 3
Classifier: Programming Language :: Python :: 3.8
Classifier: Programming Language :: Python :: 3.9
Classifier: Programming Language :: Python :: 3.10
Classifier: Programming Language :: Python :: 3.11
Classifier: Programming Language :: Python :: 3.12
